signapadpy/__init__.py
signapadpy/image.py
signapadpy-0.0.2.dist-info/DESCRIPTION.rst
signapadpy-0.0.2.dist-info/LICENSE.txt
signapadpy-0.0.2.dist-info/METADATA
signapadpy-0.0.2.dist-info/metadata.json
signapadpy-0.0.2.dist-info/RECORD
signapadpy-0.0.2.dist-info/top_level.txt
signapadpy-0.0.2.dist-info/WHEEL
