Metadata-Version: 2.0
Name: signapadpy
Version: 0.0.2
Summary: Turn output from Signature Pad into images
Home-page: https://github.com/roam/signapadpy
Author: Kevin Wetzels
Author-email: kevin@roam.be
License: BSD
Platform: UNKNOWN
Classifier: Development Status :: 4 - Beta
Classifier: Intended Audience :: Developers
Classifier: License :: OSI Approved :: BSD License
Classifier: Operating System :: OS Independent
Classifier: Programming Language :: Python
Classifier: Programming Language :: Python :: 2
Classifier: Programming Language :: Python :: 2.7
Classifier: Programming Language :: Python :: 3
Classifier: Programming Language :: Python :: 3.2
Classifier: Programming Language :: Python :: 3.3
Requires-Dist: Pillow (>=1.7)
